zExceptions/ExceptionFormatter.py
zExceptions/ITracebackSupplement.py
zExceptions/TracebackSupplement.py
zExceptions/__init__.py
zExceptions/unauthorized.py
zExceptions/tests/__init__.py
zExceptions/tests/testExceptionFormatter.py
zExceptions/tests/test___init__.py
zExceptions/tests/test_unauthorized.py
zExceptions-5.0.dist-info/LICENSE.txt
zExceptions-5.0.dist-info/METADATA
zExceptions-5.0.dist-info/WHEEL
zExceptions-5.0.dist-info/top_level.txt
zExceptions-5.0.dist-info/RECORD
